raj_operands/__init__.py
raj_operands-0.1.dist-info/licenses/LICENSE.txt
raj_operands-0.1.dist-info/METADATA
raj_operands-0.1.dist-info/WHEEL
raj_operands-0.1.dist-info/top_level.txt
raj_operands-0.1.dist-info/RECORD
