Metadata-Version: 2.4
Name: raj_operands
Version: 0.1
Summary: This package related to 2 operands are same are not by using conditional statement concepts
Author: Raj Kumar Kurra
Author-email: kraj13866@gmail.com
Classifier: Programming Language :: Python :: 3
Classifier: License :: OSI Approved :: MIT License
Classifier: Operating System :: OS Independent
License-File: LICENSE.txt
Dynamic: author
Dynamic: author-email
Dynamic: classifier
Dynamic: license-file
Dynamic: summary
